saltgang/__init__.py
saltgang/args.py
saltgang/common.py
saltgang/conf.py
saltgang/encassist.py
saltgang/fetch.py
saltgang/logger.py
saltgang/main.py
saltgang/meta.py
saltgang/panel.py
saltgang/project.py
saltgang/quickstart.py
saltgang/settings.py
saltgang/ytt.py
saltgang/conf/config.yml
saltgang/templates/c.tmpl
saltgang/templates/go.tmpl
saltgang/templates/ini.tmpl
saltgang/templates/ini2.tmpl
saltgang/templates/ini_check.tmpl
saltgang/templates/view4.tmpl
saltgang/templates/view5.tmpl
saltgang/templates/view7.tmpl
saltgang-0.1.17.dist-info/LICENSE.txt
saltgang-0.1.17.dist-info/METADATA
saltgang-0.1.17.dist-info/WHEEL
saltgang-0.1.17.dist-info/entry_points.txt
saltgang-0.1.17.dist-info/top_level.txt
saltgang-0.1.17.dist-info/RECORD
